emlinh_events/__init__.py
emlinh_events/events.py
emlinh_events-0.1.0.dist-info/METADATA
emlinh_events-0.1.0.dist-info/WHEEL
emlinh_events-0.1.0.dist-info/top_level.txt
emlinh_events-0.1.0.dist-info/RECORD
