Metadata-Version: 2.4
Name: emlinh-events
Version: 0.1.0
Summary: Shared event schemas for orchestrator messaging
Author-email: Mike Trần <hungmanh2607@gmail.com>
License: MIT
Requires-Python: >=3.10
Requires-Dist: pydantic>=2.6
